pymstodo/__init__.py
pymstodo/client.py
pymstodo/windows_zones_adapter.py
pymstodo/windows_zones_data.py
pymstodo-0.1.9.dist-info/LICENSE
pymstodo-0.1.9.dist-info/METADATA
pymstodo-0.1.9.dist-info/WHEEL
pymstodo-0.1.9.dist-info/top_level.txt
pymstodo-0.1.9.dist-info/RECORD
