Metadata-Version: 2.1
Name: pymstodo
Version: 0.1.9
Summary: Microsoft To Do API client
Home-page: https://github.com/inbalboa/pymstodo
Author: Serhiy Shliapuhin
Author-email: shlyapugin@gmail.com
License: GPLv3
Classifier: Programming Language :: Python :: 3
Classifier: Programming Language :: Python :: 3.10
Classifier: Programming Language :: Python :: 3 :: Only
Classifier: License :: OSI Approved
Classifier: License :: OSI Approved :: GNU General Public License v3 (GPLv3)
Classifier: Operating System :: OS Independent
Requires-Python: >=3.10,<4.0
License-File: LICENSE
Requires-Dist: requests-oauthlib >=1.3.0
Requires-Dist: defusedxml >=0.7.1
